scryfallscraper/__init__.py
scryfallscraper/scraper.py
scryfallscraper/bulk_scraping/__init__.py
scryfallscraper/bulk_scraping/functions.py
scryfallscraper/bulk_scraping/util.py
scryfallscraper/compression/__init__.py
scryfallscraper/compression/functions.py
scryfallscraper/sets/__init__.py
scryfallscraper/sets/functions.py
scryfallscraper/util/__init__.py
scryfallscraper/util/util.py
scryfallscraper-0.0.3.2.dist-info/METADATA
scryfallscraper-0.0.3.2.dist-info/WHEEL
scryfallscraper-0.0.3.2.dist-info/top_level.txt
scryfallscraper-0.0.3.2.dist-info/RECORD
