Metadata-Version: 2.1
Name: scryfallscraper
Version: 0.0.3.2
Summary: A way to scrape the Scryfall API without much worry.
Project-URL: Source, https://github.com/sbyt32/scryfall-scraper-scripts
Requires-Dist: requests
